Next/__init__.py
Next/main.py
bgrevbyramya-0.1.0.dist-info/METADATA
bgrevbyramya-0.1.0.dist-info/WHEEL
bgrevbyramya-0.1.0.dist-info/top_level.txt
bgrevbyramya-0.1.0.dist-info/RECORD
