Metadata-Version: 2.1
Name: bgrevbyramya
Version: 0.1.0
Summary: A simple package to remove image backgrounds using rembg.
Author: Ramya
Author-email: ramyacp97@gmail.com
Classifier: Programming Language :: Python :: 3
Classifier: License :: OSI Approved :: MIT License
Classifier: Operating System :: OS Independent
Requires-Python: >=3.7
Requires-Dist: rembg
Requires-Dist: Pillow
